{
    "CVR": {
        "cast_branch": "CVRs/0009/6c76c4078a",
        "choices": [
            {
                "name": "Nien Nunb",
                "party": "Circle Party"
            },
            {
                "name": "Chelli Lona Aphra",
                "party": "Triangle Party"
            },
            {
                "name": "Hondo Ohnaka",
                "party": "Rectangle Party"
            }
        ],
        "ggo": "GGOs/states/California/GGOs/counties/Alameda/GGOs/Parks and Recreation/Zone C",
        "max": 2,
        "name": "Park Administrator",
        "selection": [
            0,
            1
        ],
        "tally": "plurality",
        "uid": "0009"
    }
}