{
    "CVR": {
        "cast_branch": "CVRs/0052/35f34c672c",
        "choices": [
            {
                "name": "C C",
                "party": "Circle Party"
            },
            {
                "name": "D D",
                "party": "Triangle Party"
            }
        ],
        "ggo": "GGOs/states/California/GGOs/towns/Oakland",
        "max": 1,
        "name": "state senate",
        "selection": [
            0
        ],
        "tally": "plurality",
        "uid": "0052"
    }
}